bofire/__init__.py
bofire/protocols.py
bofire/version.py
bofire/benchmarks/LookupTableBenchmark.py
bofire/benchmarks/__init__.py
bofire/benchmarks/api.py
bofire/benchmarks/aspen_benchmark.py
bofire/benchmarks/benchmark.py
bofire/benchmarks/detergent.py
bofire/benchmarks/hyperopt.py
bofire/benchmarks/multi.py
bofire/benchmarks/single.py
bofire/benchmarks/data/__init__.py
bofire/benchmarks/data/aniline_cn_crosscoupling.py
bofire/benchmarks/data/photoswitches.py
bofire/data_models/__init__.py
bofire/data_models/api.py
bofire/data_models/base.py
bofire/data_models/enum.py
bofire/data_models/filters.py
bofire/data_models/types.py
bofire/data_models/unions.py
bofire/data_models/acquisition_functions/__init__.py
bofire/data_models/acquisition_functions/acquisition_function.py
bofire/data_models/acquisition_functions/api.py
bofire/data_models/constraints/__init__.py
bofire/data_models/constraints/api.py
bofire/data_models/constraints/categorical.py
bofire/data_models/constraints/condition.py
bofire/data_models/constraints/constraint.py
bofire/data_models/constraints/interpoint.py
bofire/data_models/constraints/linear.py
bofire/data_models/constraints/nchoosek.py
bofire/data_models/constraints/nonlinear.py
bofire/data_models/constraints/product.py
bofire/data_models/dataframes/__init__.py
bofire/data_models/dataframes/api.py
bofire/data_models/dataframes/dataframes.py
bofire/data_models/domain/__init__.py
bofire/data_models/domain/api.py
bofire/data_models/domain/constraints.py
bofire/data_models/domain/domain.py
bofire/data_models/domain/features.py
bofire/data_models/features/__init__.py
bofire/data_models/features/api.py
bofire/data_models/features/categorical.py
bofire/data_models/features/continuous.py
bofire/data_models/features/descriptor.py
bofire/data_models/features/discrete.py
bofire/data_models/features/engineered_feature.py
bofire/data_models/features/feature.py
bofire/data_models/features/molecular.py
bofire/data_models/features/numerical.py
bofire-0.3.1.dist-info/licenses/LICENSE
bofire-0.3.1.dist-info/METADATA
bofire-0.3.1.dist-info/WHEEL
bofire-0.3.1.dist-info/top_level.txt
bofire-0.3.1.dist-info/RECORD
