Metadata-Version: 2.4
Name: bofire
Version: 0.3.1
License: BSD-3
Project-URL: homepage, https://github.com/experimental-design/bofire
Keywords: Bayesian optimization,Multi-objective optimization,Experimental design
Classifier: Development Status :: 1 - Planning
Classifier: Programming Language :: Python :: 3 :: Only
Classifier: License :: OSI Approved :: BSD License
Classifier: Topic :: Scientific/Engineering
Classifier: Intended Audience :: Science/Research
Classifier: Intended Audience :: Developers
Requires-Python: >=3.10.0
License-File: LICENSE
Requires-Dist: numpy
Requires-Dist: pandas
Requires-Dist: pydantic>=2.5
Requires-Dist: scipy>=1.7
Requires-Dist: typing-extensions
Requires-Dist: formulaic==1.0.1
Provides-Extra: optimization
Requires-Dist: botorch>=0.16.1; extra == "optimization"
Requires-Dist: numpy; extra == "optimization"
Requires-Dist: multiprocess; extra == "optimization"
Requires-Dist: plotly; extra == "optimization"
Requires-Dist: formulaic<1.1,>=1.0.1; extra == "optimization"
Requires-Dist: cloudpickle>=2.0.0; extra == "optimization"
Requires-Dist: sympy>=1.12; extra == "optimization"
Requires-Dist: cvxpy[CLARABEL,SCIP]; extra == "optimization"
Requires-Dist: scikit-learn>=1.0.0; extra == "optimization"
Requires-Dist: pymoo>=0.6.0; extra == "optimization"
Requires-Dist: shap>=0.48.0; extra == "optimization"
Provides-Extra: entmoot
Requires-Dist: pyomo<=6.9.4; extra == "entmoot"
Requires-Dist: entmoot>=2.0.6; extra == "entmoot"
Provides-Extra: cheminfo
Requires-Dist: rdkit>=2023.3.2; extra == "cheminfo"
Requires-Dist: scikit-learn>=1.0.0; extra == "cheminfo"
Requires-Dist: mordred>=1.2.0; extra == "cheminfo"
Provides-Extra: tests
Requires-Dist: pytest; extra == "tests"
Requires-Dist: pytest-cov; extra == "tests"
Requires-Dist: papermill; extra == "tests"
Provides-Extra: docs
Requires-Dist: jupyter; extra == "docs"
Requires-Dist: jupyter-cache; extra == "docs"
Requires-Dist: matplotlib; extra == "docs"
Requires-Dist: seaborn; extra == "docs"
Provides-Extra: all
Requires-Dist: botorch>=0.16.1; extra == "all"
Requires-Dist: numpy; extra == "all"
Requires-Dist: multiprocess; extra == "all"
Requires-Dist: plotly; extra == "all"
Requires-Dist: formulaic==1.0.1; extra == "all"
Requires-Dist: cloudpickle>=2.0.0; extra == "all"
Requires-Dist: sympy>=1.12; extra == "all"
Requires-Dist: cvxpy[CLARABEL,SCIP]; extra == "all"
Requires-Dist: scikit-learn>=1.0.0; extra == "all"
Requires-Dist: entmoot>=2.0.6; extra == "all"
Requires-Dist: pyomo<=6.9.4; extra == "all"
Requires-Dist: rdkit>=2023.3.2; extra == "all"
Requires-Dist: mordred>=1.2.0; extra == "all"
Requires-Dist: mopti; extra == "all"
Requires-Dist: pytest; extra == "all"
Requires-Dist: pytest-cov; extra == "all"
Requires-Dist: papermill; extra == "all"
Requires-Dist: mkdocs; extra == "all"
Requires-Dist: mkdocs-material; extra == "all"
Requires-Dist: mkdocs-jupyter; extra == "all"
Requires-Dist: mkdocstrings>=0.18; extra == "all"
Requires-Dist: mkdocstrings-python-legacy; extra == "all"
Requires-Dist: mike; extra == "all"
Requires-Dist: jupyter; extra == "all"
Requires-Dist: matplotlib; extra == "all"
Requires-Dist: seaborn; extra == "all"
Requires-Dist: pymoo>=0.6.0; extra == "all"
Requires-Dist: shap>=0.48.0; extra == "all"
Dynamic: license-file
